signature_invariants/__init__.py
signature_invariants/invariants.py
signature_invariants_py-0.1.1.dist-info/METADATA
signature_invariants_py-0.1.1.dist-info/RECORD
signature_invariants_py-0.1.1.dist-info/WHEEL
signature_invariants_py-0.1.1.dist-info/top_level.txt
