Metadata-Version: 2.1
Name: signature-invariants-py
Version: 0.1.1
Summary: Implements certain invariants for the iterated-integrals signature.
Home-page: https://github.com/diehlj/signature-invariants-py
Author: Joscha Diehl
Author-email: UNKNOWN
License: Eclipse Public License
Platform: UNKNOWN
Requires-Dist: numpy
Requires-Dist: scipy
Requires-Dist: sympy
Requires-Dist: linear-combination-py
